POSPairWordEmbeddings/__init__.py
POSPairWordEmbeddings/setup.py
POSPairWordEmbeddings/gensim/__init__.py
POSPairWordEmbeddings/gensim/downloader.py
POSPairWordEmbeddings/gensim/interfaces.py
POSPairWordEmbeddings/gensim/matutils.py
POSPairWordEmbeddings/gensim/nosy.py
POSPairWordEmbeddings/gensim/utils.py
POSPairWordEmbeddings/gensim/corpora/__init__.py
POSPairWordEmbeddings/gensim/corpora/bleicorpus.py
POSPairWordEmbeddings/gensim/corpora/csvcorpus.py
POSPairWordEmbeddings/gensim/corpora/dictionary.py
POSPairWordEmbeddings/gensim/corpora/hashdictionary.py
POSPairWordEmbeddings/gensim/corpora/indexedcorpus.py
POSPairWordEmbeddings/gensim/corpora/lowcorpus.py
POSPairWordEmbeddings/gensim/corpora/malletcorpus.py
POSPairWordEmbeddings/gensim/corpora/mmcorpus.py
POSPairWordEmbeddings/gensim/corpora/sharded_corpus.py
POSPairWordEmbeddings/gensim/corpora/svmlightcorpus.py
POSPairWordEmbeddings/gensim/corpora/textcorpus.py
POSPairWordEmbeddings/gensim/corpora/ucicorpus.py
POSPairWordEmbeddings/gensim/corpora/wikicorpus.py
POSPairWordEmbeddings/gensim/models/__init__.py
POSPairWordEmbeddings/gensim/models/atmodel.py
POSPairWordEmbeddings/gensim/models/base_any2vec.py
POSPairWordEmbeddings/gensim/models/basemodel.py
POSPairWordEmbeddings/gensim/models/callbacks.py
POSPairWordEmbeddings/gensim/models/coherencemodel.py
POSPairWordEmbeddings/gensim/models/doc2vec.py
POSPairWordEmbeddings/gensim/models/fasttext.py
POSPairWordEmbeddings/gensim/models/hdpmodel.py
POSPairWordEmbeddings/gensim/models/keyedvectors.py
POSPairWordEmbeddings/gensim/models/lda_dispatcher.py
POSPairWordEmbeddings/gensim/models/lda_worker.py
POSPairWordEmbeddings/gensim/models/ldamodel.py
POSPairWordEmbeddings/gensim/models/ldamulticore.py
POSPairWordEmbeddings/gensim/models/ldaseqmodel.py
POSPairWordEmbeddings/gensim/models/logentropy_model.py
POSPairWordEmbeddings/gensim/models/lsi_dispatcher.py
POSPairWordEmbeddings/gensim/models/lsi_worker.py
POSPairWordEmbeddings/gensim/models/lsimodel.py
POSPairWordEmbeddings-0.0.4.dist-info/METADATA
POSPairWordEmbeddings-0.0.4.dist-info/WHEEL
POSPairWordEmbeddings-0.0.4.dist-info/top_level.txt
POSPairWordEmbeddings-0.0.4.dist-info/RECORD
